README.rst
setup.py
workonflow_bot_client/__init__.py
workonflow_bot_client/login_info.py
workonflow_bot_client/main.py
workonflow_bot_client.egg-info/PKG-INFO
workonflow_bot_client.egg-info/SOURCES.txt
workonflow_bot_client.egg-info/dependency_links.txt
workonflow_bot_client.egg-info/not-zip-safe
workonflow_bot_client.egg-info/requires.txt
workonflow_bot_client.egg-info/top_level.txt
workonflow_bot_client/lib/__init__.py
workonflow_bot_client/lib/comment/__init__.py
workonflow_bot_client/lib/comment/index.py
workonflow_bot_client/lib/stream/__init__.py
workonflow_bot_client/lib/stream/index.py
workonflow_bot_client/lib/thread/__init__.py
workonflow_bot_client/lib/thread/index.py