Metadata-Version: 1.1
Name: workonflow-bot-client
Version: 0.0.2
Summary: python bot-client for workonflow
Home-page: UNKNOWN
Author: Akbashev Rustam
Author-email: 402@onlinepbx.ru
License: MIT
Keywords: bot-client bot workonflow
Platform: UNKNOWN
Classifier: License :: OSI Approved :: MIT License
Classifier: Programming Language :: Python :: 3.6
